simcsv.py
simscv-0.0.6.dist-info/METADATA
simscv-0.0.6.dist-info/WHEEL
simscv-0.0.6.dist-info/entry_points.txt
simscv-0.0.6.dist-info/top_level.txt
simscv-0.0.6.dist-info/RECORD
