Metadata-Version: 2.1
Name: simscv
Version: 0.0.6
Summary: A simple csv reader
Home-page: https://github.com/Kanra-Ishido/simscv
Author: Kanra_Ishido
Author-email: s2222002@stu.musashino-u.ac.jp
Project-URL: Bug Tracker, https://github.com/Kanra-Ishido/simscv
Classifier: Programming Language :: Python :: 3
Classifier: License :: OSI Approved :: MIT License
Classifier: Operating System :: OS Independent
Requires-Python: >=3.7
Requires-Dist: numpy
Requires-Dist: scikit-learn
Requires-Dist: scipy
